[
  {"profileId": null, "user": {"userId": 1}, "firstName": "John", "lastName": "Doe", "phone": "123-456-7890", "profilePictureURL": "profile1.jpg"},
  {"profileId": null, "user": {"userId": 2}, "firstName": "Alice", "lastName": "Smith", "phone": "234-567-8901", "profilePictureURL": "profile2.jpg"},
  {"profileId": null, "user": {"userId": 3}, "firstName": "Bob", "lastName": "Johnson", "phone": "345-678-9012", "profilePictureURL": "profile3.jpg"},
  {"profileId": null, "user": {"userId": 4}, "firstName": "Eva", "lastName": "Williams", "phone": "456-789-0123", "profilePictureURL": "profile4.jpg"},
  {"profileId": null, "user": {"userId": 5}, "firstName": "David", "lastName": "Miller", "phone": "567-890-1234", "profilePictureURL": "profile5.jpg"},
  {"profileId": null, "user": {"userId": 6}, "firstName": "Grace", "lastName": "Brown", "phone": "678-901-2345", "profilePictureURL": "profile6.jpg"},
  {"profileId": null, "user": {"userId": 7}, "firstName": "Michael", "lastName": "Davis", "phone": "789-012-3456", "profilePictureURL": "profile7.jpg"},
  {"profileId": null, "user": {"userId": 8}, "firstName": "Olivia", "lastName": "Jones", "phone": "890-123-4567", "profilePictureURL": "profile8.jpg"},
  {"profileId": null, "user": {"userId": 9}, "firstName": "William", "lastName": "Moore", "phone": "901-234-5678", "profilePictureURL": "profile9.jpg"},
  {"profileId": null, "user": {"userId": 10}, "firstName": "Sophia", "lastName": "Taylor", "phone": "012-345-6789", "profilePictureURL": "profile10.jpg"}
]